caroa04/__init__.py
caroa04/canmessage.py
caroa04/caroa04.py
caroa04-1.0.3.dist-info/AUTHORS.rst
caroa04-1.0.3.dist-info/LICENSE
caroa04-1.0.3.dist-info/METADATA
caroa04-1.0.3.dist-info/WHEEL
caroa04-1.0.3.dist-info/top_level.txt
caroa04-1.0.3.dist-info/RECORD
