Metadata-Version: 2.1
Name: caroa04
Version: 1.0.3
Summary: Library to control the CAROA04 CAN-IO expander device from eletechsup.
Author-email: Rodolphe Mete Soyding <r.soyding@gmail.com>
Maintainer-email: Rodolphe Mete Soyding <r.soyding@gmail.com>
License: MIT license
Project-URL: bugs, https://github.com/supermete/caroa04/issues
Project-URL: changelog, https://github.com/supermete/caroa04/blob/master/changelog.md
Project-URL: homepage, https://github.com/supermete/caroa04
Classifier: Programming Language :: Python
Classifier: Programming Language :: Python :: 3.8
Classifier: Programming Language :: Python :: 3.9
Classifier: Programming Language :: Python :: 3.10
Classifier: Programming Language :: Python :: 3.11
Classifier: Programming Language :: Python :: 3 :: Only
Requires-Python: >=3.8
License-File: LICENSE
License-File: AUTHORS.rst
Requires-Dist: python-can >=3.3.0
Requires-Dist: numpy >=1.24.0
Provides-Extra: dev
Requires-Dist: coverage ; extra == 'dev'
Requires-Dist: mypy ; extra == 'dev'
Requires-Dist: pytest ; extra == 'dev'
Requires-Dist: ruff ; extra == 'dev'
